unique_sdk/__init__.py
unique_sdk/_api_requestor.py
unique_sdk/_api_resource.py
unique_sdk/_api_version.py
unique_sdk/_error.py
unique_sdk/_http_client.py
unique_sdk/_list_object.py
unique_sdk/_object_classes.py
unique_sdk/_request_options.py
unique_sdk/_unique_object.py
unique_sdk/_unique_ql.py
unique_sdk/_unique_response.py
unique_sdk/_util.py
unique_sdk/_version.py
unique_sdk/_webhook.py
unique_sdk/api_resources/__init__.py
unique_sdk/api_resources/_acronyms.py
unique_sdk/api_resources/_agentic_table.py
unique_sdk/api_resources/_chat_completion.py
unique_sdk/api_resources/_content.py
unique_sdk/api_resources/_embedding.py
unique_sdk/api_resources/_event.py
unique_sdk/api_resources/_folder.py
unique_sdk/api_resources/_group.py
unique_sdk/api_resources/_integrated.py
unique_sdk/api_resources/_llm_models.py
unique_sdk/api_resources/_mcp.py
unique_sdk/api_resources/_message.py
unique_sdk/api_resources/_message_assessment.py
unique_sdk/api_resources/_message_execution.py
unique_sdk/api_resources/_message_log.py
unique_sdk/api_resources/_search.py
unique_sdk/api_resources/_search_string.py
unique_sdk/api_resources/_short_term_memory.py
unique_sdk/api_resources/_space.py
unique_sdk/api_resources/_user.py
unique_sdk/utils/chat_history.py
unique_sdk/utils/chat_in_space.py
unique_sdk/utils/file_io.py
unique_sdk/utils/sources.py
unique_sdk/utils/token.py
unique_sdk-0.10.67.dist-info/LICENSE
unique_sdk-0.10.67.dist-info/METADATA
unique_sdk-0.10.67.dist-info/WHEEL
unique_sdk-0.10.67.dist-info/RECORD
