Metadata-Version: 2.1
Name: unique_sdk
Version: 0.10.67
Summary: 
License: MIT
Author: Martin Fadler
Author-email: martin.fadler@unique.ch
Requires-Python: >=3.11,<4.0
Classifier: License :: OSI Approved :: MIT License
Classifier: Programming Language :: Python :: 3
Classifier: Programming Language :: Python :: 3.11
Classifier: Programming Language :: Python :: 3.12
Provides-Extra: openai
Requires-Dist: openai (>=1.105.0,<2.0.0) ; extra == "openai"
Requires-Dist: requests (>=2.32.3,<3.0.0)
Requires-Dist: typing-extensions (>=4.9.0,<5.0.0)
